hydroplaningpy_test/__init__.py
hydroplaningpy_test/constant.py
hydroplaningpy_test/core_class.py
hydroplaningpy_test/general_func.py
hydroplaningpy_test/orientation.py
hydroplaningpy_test/hydro/__init__.py
hydroplaningpy_test/hydro/hydro_class.py
hydroplaningpy_test/hydro/wetted.py
hydroplaningpy_test-0.0.3.dist-info/METADATA
hydroplaningpy_test-0.0.3.dist-info/WHEEL
hydroplaningpy_test-0.0.3.dist-info/top_level.txt
hydroplaningpy_test-0.0.3.dist-info/RECORD
