Metadata-Version: 2.1
Name: hydroplaningpy-test
Version: 0.0.3
Summary: A simple package for planing hull analysis
Home-page: https://github.com/lava12005/hydroplaningpy-dev
Author: Han Beng, Koe
Author-email: hanbeng.koe@gmail.com
License: UNKNOWN
Project-URL: Bug Tracker, https://github.com/pypa/sampleproject/issues
Platform: UNKNOWN
Classifier: Programming Language :: Python :: 3
Classifier: License :: OSI Approved :: MIT License
Classifier: Operating System :: OS Independent
Requires-Python: >=3.6
